hidb/__init__.py
hidb/db.py
hidb/filestoredb.py
hidb/wrapper.py
tests/__init__.py
tests/test_filestore.py
hidb-0.0.2.dist-info/LICENSE
hidb-0.0.2.dist-info/METADATA
hidb-0.0.2.dist-info/WHEEL
hidb-0.0.2.dist-info/top_level.txt
hidb-0.0.2.dist-info/RECORD
