Metadata-Version: 2.1
Name: hidb
Version: 0.0.2
Summary: It is a file based key value data store 
Home-page: https://github.com/sk-ip/hidb
Author: Sudhanshu Kumar
Author-email: sudhanshukumar5459@gmail.com
License: UNKNOWN
Platform: UNKNOWN
Classifier: Programming Language :: Python :: 3
Classifier: License :: OSI Approved :: MIT License
Classifier: Operating System :: OS Independent
Requires-Python: >=3.6
